data/__init__.py
data/util/__init__.py
data/util/database.py
data/util/event.py
database_event-0.1.3.dist-info/METADATA
database_event-0.1.3.dist-info/WHEEL
database_event-0.1.3.dist-info/top_level.txt
database_event-0.1.3.dist-info/RECORD
