Metadata-Version: 2.1
Name: database-event
Version: 0.1.3
Summary: Esse pacote tem como função facilitar a execução paralela e distribuida de funções apply pandas
Home-page: https://github.com/Augusto-cmk/Database
Author: Augusto-cmk
Author-email: pedroaugustoms14@gmail.com
Classifier: Programming Language :: Python :: 3
Requires-Dist: numpy
Requires-Dist: pandas
Requires-Dist: tabulate ==0.9.0
Requires-Dist: readchar ==4.2.0
